doc/Makefile
doc/conf.py
doc/configuration.rst
doc/example_usage.rst
doc/index.rst
doc/installation.rst
doc/make.bat
doc/readme.rst
doc/usage.rst
doc/_static/css/extra.css
doc/input/coverage_data.xml
mlx/treemap/__init__.py
mlx/treemap/_version.py
mlx/treemap/treemap.py
mlx/treemap/treemap_directive.py
mlx_treemap-1.1.0.dist-info/licenses/LICENSE
mlx_treemap-1.1.0.dist-info/METADATA
mlx_treemap-1.1.0.dist-info/WHEEL
mlx_treemap-1.1.0.dist-info/top_level.txt
mlx_treemap-1.1.0.dist-info/RECORD
