Metadata-Version: 2.4
Name: mlx.treemap
Version: 1.1.0
Summary: Sphinx extension to generate a treemap of Cobertura data
Author-email: Jasper Craeghs <jce@melexis.com>
License-Expression: Apache-2.0
Project-URL: Homepage, https://github.com/melexis/treemap
Project-URL: Repository, https://github.com/melexis/treemap
Project-URL: Bug Tracker, https://github.com/melexis/treemap/issues
Keywords: cobertura,treemap,test coverage,visualization,sphinx
Classifier: Development Status :: 4 - Beta
Classifier: Environment :: Console
Classifier: Environment :: Web Environment
Classifier: Framework :: Sphinx :: Extension
Classifier: Intended Audience :: Developers
Classifier: Operating System :: OS Independent
Classifier: Programming Language :: Python
Classifier: Programming Language :: Python :: 3
Classifier: Programming Language :: Python :: 3.9
Classifier: Programming Language :: Python :: 3.10
Classifier: Programming Language :: Python :: 3.11
Classifier: Programming Language :: Python :: 3.12
Classifier: Programming Language :: Python :: 3.13
Classifier: Topic :: Documentation
Classifier: Topic :: Documentation :: Sphinx
Classifier: Topic :: Utilities
Requires-Python: >=3.9
License-File: LICENSE
Requires-Dist: sphinx>=5.0
Requires-Dist: plotly>=5.24.1
Requires-Dist: kaleido>=0.2.1
Requires-Dist: pandas
Dynamic: license-file
